{"cameraMode":{"drawMode":0,"name":"Shaded","section":"Shading Mode"},"sceneLighting":true,"audioPlay":false,"sceneViewState":{"m_AlwaysRefresh":false,"showFog":true,"showSkybox":true,"showFlares":true,"showImageEffects":true,"showParticleSystems":true,"showVisualEffectGraphs":true,"m_FxEnabled":true},"in2DMode":false,"pivot":{"x":-2.656493902206421,"y":0.8315844535827637,"z":-0.39649295806884768},"rotation":{"x":0.006239162292331457,"y":-0.9859049320220947,"z":0.16356541216373444,"w":0.03911101818084717},"size":6.573060035705566,"orthographic":false}